jsend/__init__.py
json_send-0.1.0.dist-info/LICENSE
json_send-0.1.0.dist-info/METADATA
json_send-0.1.0.dist-info/WHEEL
json_send-0.1.0.dist-info/top_level.txt
json_send-0.1.0.dist-info/RECORD
